{
  "users": [
    {
      "firstName": "homer",
      "lastName": "simpson",
      "email": "homer@simpson.com",
      "password": "secret",
      "id": "3ad52697-6d98-4d80-8273-084de55a86c0"
    },
    {
      "firstName": "marge",
      "lastName": "simpson",
      "email": "marge@simpson.com",
      "password": "secret",
      "id": "2b6f0989-7b7f-4a38-ad26-aa06b922d751"
    },
    {
      "firstName": "tommy",
      "lastName": "condon",
      "email": "tcmedion@outlook.ie",
      "password": "password",
      "id": "965940a7-cbe9-4f2d-9371-e43da8c0a101"
    },
    {
      "firstName": "test",
      "lastName": "name",
      "email": "tcondon12@icloud.com",
      "password": "starsign",
      "id": "ecc401ed-2ee6-4d52-b569-a32a62d8bd4d"
    },
    {
      "firstName": "john",
      "lastName": "hopkins",
      "email": "johnhopkins@wit.ie",
      "password": "secret6",
      "id": "cbff8c82-0b74-40b3-a340-acd484bf3551"
    },
    {
      "firstName": "tommy",
      "lastName": "condon",
      "email": "user@wit.ie",
      "password": "hello",
      "id": "c2b317b9-270e-4b49-af38-ed90e4842ed9"
    },
    {
      "firstName": "account",
      "lastName": "forPicture",
      "email": "user1@wit.ie",
      "password": "hello1",
      "id": "a97865ea-72fe-4311-af5b-42f979542767"
    },
    {
      "firstName": "signup",
      "lastName": "test",
      "email": "user2@wit.ie",
      "password": "tester",
      "id": "8a34e322-0d55-43a1-aacc-314f2bd4e24f"
    },
    {
      "firstName": "john",
      "lastName": "condon",
      "email": "user45@wit.ie",
      "password": "etcetc",
      "id": "e4c91a53-ed96-4859-968f-cfa4c38dee78"
    },
    {
      "firstName": "teste",
      "lastName": "testteser",
      "email": "useruser@gmail.com",
      "password": "etc",
      "id": "9bb07c5a-3c27-4acc-ba08-fe195a753684"
    }
  ]
}